MANIFEST.in
README.txt
setup.cfg
setup.py
docs/HISTORY.txt
pcommerce/__init__.py
pcommerce.shipment.haulage.egg-info/PKG-INFO
pcommerce.shipment.haulage.egg-info/SOURCES.txt
pcommerce.shipment.haulage.egg-info/dependency_links.txt
pcommerce.shipment.haulage.egg-info/entry_points.txt
pcommerce.shipment.haulage.egg-info/namespace_packages.txt
pcommerce.shipment.haulage.egg-info/not-zip-safe
pcommerce.shipment.haulage.egg-info/requires.txt
pcommerce.shipment.haulage.egg-info/top_level.txt
pcommerce/shipment/__init__.py
pcommerce/shipment/haulage/__init__.py
pcommerce/shipment/haulage/configure.zcml
pcommerce/shipment/haulage/data.py
pcommerce/shipment/haulage/interfaces.py
pcommerce/shipment/haulage/plugin.py
pcommerce/shipment/haulage/browser/__init__.py
pcommerce/shipment/haulage/browser/base.py
pcommerce/shipment/haulage/browser/configure.zcml
pcommerce/shipment/haulage/browser/confirmation.pt
pcommerce/shipment/haulage/browser/confirmation.py
pcommerce/shipment/haulage/browser/icon.gif
pcommerce/shipment/haulage/browser/logo.gif
pcommerce/shipment/haulage/browser/overview.pt
pcommerce/shipment/haulage/browser/overview.py
pcommerce/shipment/haulage/browser/shipment.pt
pcommerce/shipment/haulage/browser/shipment.py
pcommerce/shipment/haulage/i18n/pcommerce-de.mo
pcommerce/shipment/haulage/i18n/pcommerce-de.po
pcommerce/shipment/haulage/i18n/pcommerce-fr.mo
pcommerce/shipment/haulage/i18n/pcommerce-fr.po
pcommerce/shipment/haulage/i18n/pcommerce-nl.mo
pcommerce/shipment/haulage/i18n/pcommerce-nl.po
pcommerce/shipment/haulage/i18n/pcommerce.pot
pcommerce/shipment/haulage/profiles/default/metadata.xml
pcommerce/shipment/haulage/profiles/default/propertiestool.xml